cryptoparser/__init__.py
cryptoparser/__setup__.py
cryptoparser/common/__init__.py
cryptoparser/common/base.py
cryptoparser/common/classes.py
cryptoparser/common/exception.py
cryptoparser/common/field.py
cryptoparser/common/parse.py
cryptoparser/common/utils.py
cryptoparser/common/x509.py
cryptoparser/dnsrec/__init__.py
cryptoparser/dnsrec/record.py
cryptoparser/dnsrec/txt.py
cryptoparser/httpx/__init__.py
cryptoparser/httpx/header.py
cryptoparser/httpx/parse.py
cryptoparser/httpx/version.py
cryptoparser/ssh/__init__.py
cryptoparser/ssh/key.py
cryptoparser/ssh/record.py
cryptoparser/ssh/subprotocol.py
cryptoparser/ssh/version.py
cryptoparser/tls/__init__.py
cryptoparser/tls/algorithm.py
cryptoparser/tls/ciphersuite.py
cryptoparser/tls/extension.py
cryptoparser/tls/grease.py
cryptoparser/tls/ldap.py
cryptoparser/tls/mysql.py
cryptoparser/tls/openvpn.py
cryptoparser/tls/postgresql.py
cryptoparser/tls/rdp.py
cryptoparser/tls/record.py
cryptoparser/tls/subprotocol.py
cryptoparser/tls/version.py
cryptoparser-1.0.2.dist-info/licenses/LICENSE.txt
docs/.gitignore
docs/changelog.rst
docs/conf.py
docs/development.rst
docs/features.rst
docs/index.rst
test/__init__.py
test/common/__init__.py
test/common/classes.py
test/common/test_algorithm.py
test/common/test_base.py
test/common/test_classes.py
test/common/test_exception.py
test/common/test_field.py
test/common/test_parse.py
test/common/test_utils.py
test/common/test_x509.py
test/common/certs/ecc256.badssl.com.pem
test/common/certs/rsa8192.badssl.com.pem
test/common/certs/rsa8192.badssl.com_certificate.crt
test/common/certs/rsa8192.badssl.com_root_ca.crt
test/common/certs/snakeoil_cert.pem
test/dnsrec/__init__.py
test/dnsrec/test_record.py
test/dnsrec/test_txt.py
test/httpx/__init__.py
test/httpx/classes.py
test/httpx/test_header.py
test/httpx/test_version.py
test/ssh/__init__.py
test/ssh/test_ciphersuites.py
test/ssh/test_key.py
test/ssh/test_record.py
test/ssh/test_subprotocol.py
test/ssh/test_version.py
test/tls/__init__.py
test/tls/classes.py
test/tls/test_alert.py
cryptoparser-1.0.2.dist-info/METADATA
cryptoparser-1.0.2.dist-info/WHEEL
cryptoparser-1.0.2.dist-info/top_level.txt
cryptoparser-1.0.2.dist-info/RECORD
