Metadata-Version: 2.4
Name: CryptoParser
Version: 1.0.2
Summary: An analysis oriented security protocol parser and generator
Author-email: Szilárd Pfeiffer <coroner@pfeifferszilard.hu>
Maintainer-email: Szilárd Pfeiffer <coroner@pfeifferszilard.hu>
License: MPL-2.0
Project-URL: Homepage, https://gitlab.com/coroner/cryptoparser
Project-URL: Changelog, https://cryptoparser.readthedocs.io/en/latest/changelog
Project-URL: Documentation, https://cryptoparser.readthedocs.io/en/latest/
Project-URL: Issues, https://gitlab.com/coroner/cryptoparser/-/issues
Project-URL: Source, https://gitlab.com/coroner/cryptoparser
Keywords: ssl,tls,gost,ja3,ldap,rdp,ssh,hsts,dns
Classifier: Development Status :: 5 - Production/Stable
Classifier: Environment :: Console
Classifier: Framework :: tox
Classifier: Intended Audience :: Information Technology
Classifier: Intended Audience :: Science/Research
Classifier: Intended Audience :: System Administrators
Classifier: Natural Language :: English
Classifier: Operating System :: MacOS
Classifier: Operating System :: Microsoft :: Windows
Classifier: Operating System :: POSIX
Classifier: Programming Language :: Python :: 3.9
Classifier: Programming Language :: Python :: 3.10
Classifier: Programming Language :: Python :: 3.11
Classifier: Programming Language :: Python :: 3.12
Classifier: Programming Language :: Python :: 3.13
Classifier: Programming Language :: Python :: 3.14
Classifier: Programming Language :: Python :: Implementation :: CPython
Classifier: Programming Language :: Python :: Implementation :: PyPy
Classifier: Programming Language :: Python
Classifier: Topic :: Internet
Classifier: Topic :: Security
Classifier: Topic :: Security :: Cryptography
Classifier: Topic :: Software Development :: Libraries :: Python Modules
Classifier: Topic :: Software Development :: Testing :: Traffic Generation
Classifier: Topic :: Software Development :: Testing
License-File: LICENSE.txt
Requires-Dist: asn1crypto
Requires-Dist: attrs
Requires-Dist: cryptodatahub==1.0.2
Requires-Dist: urllib3
Provides-Extra: tests
Requires-Dist: pyfakefs; extra == "tests"
Provides-Extra: docs
Requires-Dist: sphinx; extra == "docs"
Requires-Dist: sphinx-sitemap; extra == "docs"
Dynamic: license-file
